[
	{
		"name": "Bonner Gill",
		"email": "bonnergill@zytrex.com",
		"phone": "010-8735-4027"
	},
	{
		"name": "Mccormick Miller",
		"email": "mccormickmiller@zytrex.com",
		"phone": "010-9594-4136"
	},
	{
		"name": "Henry Davis",
		"email": "henrydavis@zytrex.com",
		"phone": "010-8454-9825"
	},
	{
		"name": "Constance Turner",
		"email": "constanceturner@zytrex.com",
		"phone": "010-9924-7222"
	},
	{
		"name": "Burt Nicholson",
		"email": "burtnicholson@zytrex.com",
		"phone": "010-8485-1322"
	},
	{
		"name": "Parsons Ryan",
		"email": "parsonsryan@zytrex.com",
		"phone": "010-9475-1521"
	},
	{
		"name": "Ingram Hensley",
		"email": "ingramhensley@zytrex.com",
		"phone": "010-8855-9227"
	},
	{
		"name": "Humphrey Green",
		"email": "humphreygreen@zytrex.com",
		"phone": "010-9244-7236"
	},
	{
		"name": "Lucy Sears",
		"email": "lucysears@zytrex.com",
		"phone": "010-8415-9038"
	},
	{
		"name": "Jewel Hardin",
		"email": "jewelhardin@zytrex.com",
		"phone": "010-8564-5324"
	},
	{
		"name": "Ashley Benson",
		"email": "ashleybenson@zytrex.com",
		"phone": "010-9184-8230"
	},
	{
		"name": "Leann Alvarado",
		"email": "leannalvarado@zytrex.com",
		"phone": "010-8654-7334"
	},
	{
		"name": "Violet Hahn",
		"email": "violethahn@zytrex.com",
		"phone": "010-8915-8724"
	},
	{
		"name": "Isabel Oneill",
		"email": "isabeloneill@zytrex.com",
		"phone": "010-9834-3623"
	},
	{
		"name": "Hughes Forbes",
		"email": "hughesforbes@zytrex.com",
		"phone": "010-9605-4022"
	},
	{
		"name": "Stephens Mcbride",
		"email": "stephensmcbride@zytrex.com",
		"phone": "010-9815-5525"
	},
	{
		"name": "Wolfe Humphrey",
		"email": "wolfehumphrey@zytrex.com",
		"phone": "010-8515-0626"
	},
	{
		"name": "Morrow Colon",
		"email": "morrowcolon@zytrex.com",
		"phone": "010-8414-8733"
	},
	{
		"name": "Tricia Webster",
		"email": "triciawebster@zytrex.com",
		"phone": "010-9654-0226"
	},
	{
		"name": "Sweet Mckee",
		"email": "sweetmckee@zytrex.com",
		"phone": "010-9745-8337"
	},
	{
		"name": "Blevins Mathis",
		"email": "blevinsmathis@zytrex.com",
		"phone": "010-9234-2037"
	},
	{
		"name": "Hannah Buck",
		"email": "hannahbuck@zytrex.com",
		"phone": "010-8514-4431"
	},
	{
		"name": "Hurst Reynolds",
		"email": "hurstreynolds@zytrex.com",
		"phone": "010-8255-8823"
	},
	{
		"name": "Winnie Maxwell",
		"email": "winniemaxwell@zytrex.com",
		"phone": "010-8095-7035"
	},
	{
		"name": "Araceli Kirk",
		"email": "aracelikirk@zytrex.com",
		"phone": "010-9654-5432"
	},
	{
		"name": "Allie Slater",
		"email": "allieslater@zytrex.com",
		"phone": "010-8594-2622"
	},
	{
		"name": "Knight Barrera",
		"email": "knightbarrera@zytrex.com",
		"phone": "010-8985-7235"
	},
	{
		"name": "Owens Burch",
		"email": "owensburch@zytrex.com",
		"phone": "010-9104-7924"
	},
	{
		"name": "Aguilar Meadows",
		"email": "aguilarmeadows@zytrex.com",
		"phone": "010-9274-5736"
	},
	{
		"name": "Goldie Garner",
		"email": "goldiegarner@zytrex.com",
		"phone": "010-9644-3839"
	},
	{
		"name": "Alfreda Giles",
		"email": "alfredagiles@zytrex.com",
		"phone": "010-8514-1020"
	},
	{
		"name": "Carolina Crane",
		"email": "carolinacrane@zytrex.com",
		"phone": "010-8254-1329"
	},
	{
		"name": "Berger Beard",
		"email": "bergerbeard@zytrex.com",
		"phone": "010-8315-6222"
	},
	{
		"name": "Hollie Dickerson",
		"email": "holliedickerson@zytrex.com",
		"phone": "010-8365-4622"
	},
	{
		"name": "Misty Oliver",
		"email": "mistyoliver@zytrex.com",
		"phone": "010-8074-0834"
	},
	{
		"name": "Maryellen Marks",
		"email": "maryellenmarks@zytrex.com",
		"phone": "010-8755-5732"
	},
	{
		"name": "Lara Hines",
		"email": "larahines@zytrex.com",
		"phone": "010-8645-5222"
	},
	{
		"name": "Della Donaldson",
		"email": "delladonaldson@zytrex.com",
		"phone": "010-8094-1739"
	},
	{
		"name": "Tabatha Phelps",
		"email": "tabathaphelps@zytrex.com",
		"phone": "010-8404-4730"
	},
	{
		"name": "Rosanne Keith",
		"email": "rosannekeith@zytrex.com",
		"phone": "010-9225-3224"
	},
	{
		"name": "Sarah Mayo",
		"email": "sarahmayo@zytrex.com",
		"phone": "010-8535-1336"
	},
	{
		"name": "Carrillo Jennings",
		"email": "carrillojennings@zytrex.com",
		"phone": "010-9664-7924"
	},
	{
		"name": "Rene Chase",
		"email": "renechase@zytrex.com",
		"phone": "010-9584-1521"
	},
	{
		"name": "Lenore Rogers",
		"email": "lenorerogers@zytrex.com",
		"phone": "010-9384-3239"
	},
	{
		"name": "Willie Cochran",
		"email": "williecochran@zytrex.com",
		"phone": "010-8604-1235"
	},
	{
		"name": "Jenny Shaw",
		"email": "jennyshaw@zytrex.com",
		"phone": "010-9145-4836"
	},
	{
		"name": "Barker Ballard",
		"email": "barkerballard@zytrex.com",
		"phone": "010-8624-2135"
	},
	{
		"name": "Fry Petty",
		"email": "frypetty@zytrex.com",
		"phone": "010-9284-3933"
	},
	{
		"name": "Kerr Norton",
		"email": "kerrnorton@zytrex.com",
		"phone": "010-9125-0427"
	},
	{
		"name": "Dolly Browning",
		"email": "dollybrowning@zytrex.com",
		"phone": "010-9184-3532"
	},
	{
		"name": "Margo Kaufman",
		"email": "margokaufman@zytrex.com",
		"phone": "010-9454-1832"
	},
	{
		"name": "Henderson Gray",
		"email": "hendersongray@zytrex.com",
		"phone": "010-9895-7126"
	},
	{
		"name": "Dotson Jensen",
		"email": "dotsonjensen@zytrex.com",
		"phone": "010-8824-1128"
	},
	{
		"name": "Lynnette Church",
		"email": "lynnettechurch@zytrex.com",
		"phone": "010-8965-6933"
	},
	{
		"name": "Roberson Dotson",
		"email": "robersondotson@zytrex.com",
		"phone": "010-8675-8522"
	},
	{
		"name": "Patrick Terry",
		"email": "patrickterry@zytrex.com",
		"phone": "010-8984-7035"
	},
	{
		"name": "Price Haley",
		"email": "pricehaley@zytrex.com",
		"phone": "010-9214-5421"
	},
	{
		"name": "Minnie Bell",
		"email": "minniebell@zytrex.com",
		"phone": "010-9015-6031"
	},
	{
		"name": "Ollie Bernard",
		"email": "olliebernard@zytrex.com",
		"phone": "010-9465-0028"
	},
	{
		"name": "Pope Nolan",
		"email": "popenolan@zytrex.com",
		"phone": "010-8464-3939"
	},
	{
		"name": "Maryann Mejia",
		"email": "maryannmejia@zytrex.com",
		"phone": "010-9495-2526"
	},
	{
		"name": "Jessica Ferrell",
		"email": "jessicaferrell@zytrex.com",
		"phone": "010-8925-8834"
	},
	{
		"name": "Hogan Mcfadden",
		"email": "hoganmcfadden@zytrex.com",
		"phone": "010-8654-1223"
	},
	{
		"name": "Randi Norris",
		"email": "randinorris@zytrex.com",
		"phone": "010-8505-1831"
	},
	{
		"name": "Sophie Rodgers",
		"email": "sophierodgers@zytrex.com",
		"phone": "010-8334-1831"
	},
	{
		"name": "Paula Stein",
		"email": "paulastein@zytrex.com",
		"phone": "010-8284-0124"
	},
	{
		"name": "Nona Moses",
		"email": "nonamoses@zytrex.com",
		"phone": "010-9855-2324"
	},
	{
		"name": "Bailey Barker",
		"email": "baileybarker@zytrex.com",
		"phone": "010-9784-0427"
	},
	{
		"name": "Eliza Warren",
		"email": "elizawarren@zytrex.com",
		"phone": "010-8185-1634"
	},
	{
		"name": "Amie Hancock",
		"email": "amiehancock@zytrex.com",
		"phone": "010-9144-7437"
	},
	{
		"name": "Ellen Douglas",
		"email": "ellendouglas@zytrex.com",
		"phone": "010-8214-5321"
	},
	{
		"name": "Stevenson Bray",
		"email": "stevensonbray@zytrex.com",
		"phone": "010-9644-4722"
	},
	{
		"name": "Nieves Carlson",
		"email": "nievescarlson@zytrex.com",
		"phone": "010-8965-3525"
	},
	{
		"name": "Marks Snider",
		"email": "markssnider@zytrex.com",
		"phone": "010-9894-8834"
	},
	{
		"name": "Thelma Berry",
		"email": "thelmaberry@zytrex.com",
		"phone": "010-9984-1625"
	},
	{
		"name": "Marci Snow",
		"email": "marcisnow@zytrex.com",
		"phone": "010-8425-9521"
	},
	{
		"name": "Donaldson Walton",
		"email": "donaldsonwalton@zytrex.com",
		"phone": "010-8524-4320"
	},
	{
		"name": "Simpson Robles",
		"email": "simpsonrobles@zytrex.com",
		"phone": "010-8925-4634"
	},
	{
		"name": "Luna Alvarez",
		"email": "lunaalvarez@zytrex.com",
		"phone": "010-9234-1430"
	},
	{
		"name": "Lee Glass",
		"email": "leeglass@zytrex.com",
		"phone": "010-8714-7127"
	},
	{
		"name": "Dorthy Long",
		"email": "dorthylong@zytrex.com",
		"phone": "010-9165-2026"
	},
	{
		"name": "Burke Parks",
		"email": "burkeparks@zytrex.com",
		"phone": "010-8345-7229"
	},
	{
		"name": "Warner Atkins",
		"email": "warneratkins@zytrex.com",
		"phone": "010-8255-1539"
	},
	{
		"name": "Mavis Moss",
		"email": "mavismoss@zytrex.com",
		"phone": "010-8035-5732"
	},
	{
		"name": "Dudley Swanson",
		"email": "dudleyswanson@zytrex.com",
		"phone": "010-8004-6339"
	},
	{
		"name": "Bessie Cobb",
		"email": "bessiecobb@zytrex.com",
		"phone": "010-9194-3726"
	},
	{
		"name": "Marta Benjamin",
		"email": "martabenjamin@zytrex.com",
		"phone": "010-8515-9422"
	},
	{
		"name": "Horn Morris",
		"email": "hornmorris@zytrex.com",
		"phone": "010-9335-6935"
	},
	{
		"name": "Consuelo Kidd",
		"email": "consuelokidd@zytrex.com",
		"phone": "010-8154-3021"
	},
	{
		"name": "Rosemarie Rosa",
		"email": "rosemarierosa@zytrex.com",
		"phone": "010-8455-0220"
	},
	{
		"name": "Fannie Avila",
		"email": "fannieavila@zytrex.com",
		"phone": "010-9525-3028"
	},
	{
		"name": "Kari Huffman",
		"email": "karihuffman@zytrex.com",
		"phone": "010-8495-5423"
	},
	{
		"name": "Jewell Higgins",
		"email": "jewellhiggins@zytrex.com",
		"phone": "010-9985-7620"
	},
	{
		"name": "Nettie Cruz",
		"email": "nettiecruz@zytrex.com",
		"phone": "010-8904-3430"
	},
	{
		"name": "Perez James",
		"email": "perezjames@zytrex.com",
		"phone": "010-9544-3723"
	},
	{
		"name": "Morales Gaines",
		"email": "moralesgaines@zytrex.com",
		"phone": "010-9315-4722"
	},
	{
		"name": "Huber Mccray",
		"email": "hubermccray@zytrex.com",
		"phone": "010-9174-2427"
	},
	{
		"name": "Norman Vincent",
		"email": "normanvincent@zytrex.com",
		"phone": "010-8164-4920"
	},
	{
		"name": "Calhoun Massey",
		"email": "calhounmassey@zytrex.com",
		"phone": "010-8895-8929"
	},
	{
		"name": "Katelyn Barnes",
		"email": "katelynbarnes@zytrex.com",
		"phone": "010-8695-5831"
	}
]